tokeye/__init__.py
tokeye/analysis/__init__.py
tokeye/analysis/batch_analysis.py
tokeye/app/__init__.py
tokeye/app/__main__.py
tokeye/app/analyze/__init__.py
tokeye/app/analyze/analyze.py
tokeye/app/analyze/load.py
tokeye/app/analyze/transforms.py
tokeye/app/analyze/visualize.py
tokeye/app/processing/QUICKSTART.md
tokeye/app/processing/README.md
tokeye/app/processing/__init__.py
tokeye/app/processing/inference.py
tokeye/app/processing/postprocess.py
tokeye/app/processing/tiling.py
tokeye/app/tabs/__init__.py
tokeye/app/tabs/annotate.py
tokeye/app/tabs/utilities.py
tokeye/app/utils/__init__.py
tokeye/app/utils/analyze.py
tokeye/app/utils/theme.py
tokeye/extra/D3D/__init__.py
tokeye/extra/D3D/ece_rolloff.py
tokeye/extra/eval/D3D/__init__.py
tokeye/extra/eval/D3D/methods_pcg.py
tokeye/extra/eval/silbidopy/__init__.py
tokeye/extra/eval/silbidopy/data.py
tokeye/extra/eval/silbidopy/eval.py
tokeye/extra/eval/silbidopy/readBinaries.py
tokeye/extra/eval/silbidopy/render.py
tokeye/extra/eval/silbidopy/sigproc.py
tokeye/extra/eval/silbidopy/writeBinaries.py
tokeye/models/__init__.py
tokeye/models/ae_tf_boxrcnn/config_ae_tf_boxrcnn.py
tokeye/models/ae_tf_boxrcnn/model_ae_tf_boxrcnn.py
tokeye/models/ae_tf_maskrcnn/config_ae_tf_maskrcnn.py
tokeye/models/ae_tf_maskrcnn/model_ae_tf_maskrcnn.py
tokeye/models/big_tf_unet/config_big_tf_unet.py
tokeye/models/big_tf_unet/model_big_tf_unet.py
tokeye/models/modules/__init__.py
tokeye/models/modules/bsn.py
tokeye/models/modules/nn.py
tokeye/models/modules/unet.py
tokeye/training/big_tf_unet/README.md
tokeye/training/big_tf_unet/__init__.py
tokeye/training/big_tf_unet/config/paths.yaml
tokeye/training/big_tf_unet/step_0a_extract_faithdata.py
tokeye/training/big_tf_unet/step_0b_filter_faithdata.py
tokeye/training/big_tf_unet/step_0c_convert_faithdata.py
tokeye/training/big_tf_unet/step_1a_make_timeseries.py
tokeye/training/big_tf_unet/step_2a_make_spectrogram.py
tokeye/training/big_tf_unet/step_2b_filter_spectrogram.py
tokeye-0.9.0.dist-info/WHEEL
tokeye-0.9.0.dist-info/METADATA
tokeye-0.9.0.dist-info/RECORD
