Metadata-Version: 2.3
Name: tokeye
Version: 0.9.0
Summary: Add your description here
Requires-Dist: gradio
Requires-Dist: numpy
Requires-Dist: scipy
Requires-Dist: torch
Requires-Dist: torchcodec
Requires-Dist: torchvision
Requires-Dist: torchinfo
Requires-Dist: omegaconf
Requires-Dist: tables
Requires-Dist: pydantic
Requires-Dist: mypy ; extra == 'dev'
Requires-Dist: pytest ; extra == 'dev'
Requires-Dist: pytest-cov ; extra == 'dev'
Requires-Dist: pytest-xdist ; extra == 'dev'
Requires-Dist: ruff ; extra == 'dev'
Requires-Dist: ipykernel ; extra == 'dev'
Requires-Dist: ipywidgets ; extra == 'dev'
Requires-Dist: matplotlib ; extra == 'dev'
Requires-Dist: wavio ; extra == 'dev'
Requires-Dist: h5py ; extra == 'dev'
Requires-Dist: fusionaihub ; extra == 'dev'
Requires-Dist: scikit-learn ; extra == 'dev'
Requires-Dist: lightning ; extra == 'train'
Requires-Python: >=3.13
Provides-Extra: dev
Provides-Extra: train
